{
  "prev_date": "2026-06-17",
  "curr_date": "2026-06-18",
  "n_common": 51,
  "appeared": 11,
  "disappeared": 60,
  "newly_booked": 62,
  "freed": 23,
  "net": 39,
  "days": 1,
  "net_per_day": 39.0,
  "lead_buckets": {
    "0-14": 15,
    "15-30": 8,
    "31-60": 14,
    "61+": 18
  },
  "per_listing": {
    "1676654178217328507": {
      "nb": 1,
      "fr": 0,
      "newly": [
        "2026-06-17"
      ]
    },
    "1486868392433886844": {
      "nb": 1,
      "fr": 0,
      "newly": [
        "2026-06-20"
      ]
    },
    "33765863": {
      "nb": 1,
      "fr": 0,
      "newly": [
        "2026-06-17"
      ]
    },
    "3048611": {
      "nb": 0,
      "fr": 1,
      "newly": []
    },
    "1468933909460595941": {
      "nb": 1,
      "fr": 0,
      "newly": [
        "2026-06-20"
      ]
    },
    "1585558741481354438": {
      "nb": 2,
      "fr": 0,
      "newly": [
        "2026-07-01",
        "2026-07-02"
      ]
    },
    "1689110920890832096": {
      "nb": 9,
      "fr": 0,
      "newly": [
        "2026-08-01",
        "2026-08-02",
        "2026-08-03",
        "2026-08-04",
        "2026-08-05",
        "2026-08-06",
        "2026-08-07",
        "2026-08-08",
        "2026-08-09"
      ]
    },
    "50480093": {
      "nb": 4,
      "fr": 0,
      "newly": [
        "2026-06-30",
        "2026-07-01",
        "2026-08-03",
        "2026-08-04"
      ]
    },
    "894589562626618298": {
      "nb": 2,
      "fr": 0,
      "newly": [
        "2026-07-18",
        "2026-07-19"
      ]
    },
    "562804269364969591": {
      "nb": 4,
      "fr": 3,
      "newly": [
        "2026-06-17",
        "2026-08-27",
        "2026-08-28",
        "2026-08-29"
      ]
    },
    "54026364": {
      "nb": 1,
      "fr": 0,
      "newly": [
        "2026-06-17"
      ]
    },
    "1115077276035210469": {
      "nb": 2,
      "fr": 3,
      "newly": [
        "2026-09-14",
        "2026-09-15"
      ]
    },
    "1702974823040774754": {
      "nb": 0,
      "fr": 4,
      "newly": []
    },
    "22907692": {
      "nb": 7,
      "fr": 0,
      "newly": [
        "2026-07-13",
        "2026-07-14",
        "2026-07-15",
        "2026-09-01",
        "2026-09-02",
        "2026-09-03",
        "2026-09-04"
      ]
    },
    "1564484691930992765": {
      "nb": 3,
      "fr": 0,
      "newly": [
        "2026-10-01",
        "2026-10-02",
        "2026-10-03"
      ]
    },
    "661388249047802904": {
      "nb": 1,
      "fr": 0,
      "newly": [
        "2026-06-17"
      ]
    },
    "1273427428259625862": {
      "nb": 3,
      "fr": 0,
      "newly": [
        "2026-07-18",
        "2026-07-19",
        "2026-07-20"
      ]
    },
    "2705209": {
      "nb": 0,
      "fr": 2,
      "newly": []
    },
    "1464618562724127771": {
      "nb": 1,
      "fr": 0,
      "newly": [
        "2026-06-17"
      ]
    },
    "1109303379962375853": {
      "nb": 1,
      "fr": 0,
      "newly": [
        "2026-06-19"
      ]
    },
    "1530995836681783716": {
      "nb": 0,
      "fr": 2,
      "newly": []
    },
    "1413141196990704999": {
      "nb": 3,
      "fr": 0,
      "newly": [
        "2026-11-26",
        "2026-11-27",
        "2026-11-28"
      ]
    },
    "47531507": {
      "nb": 5,
      "fr": 8,
      "newly": [
        "2026-06-21",
        "2026-06-30",
        "2026-07-01",
        "2026-07-02",
        "2026-09-14"
      ]
    },
    "1530998928240164939": {
      "nb": 3,
      "fr": 0,
      "newly": [
        "2026-06-25",
        "2026-06-26",
        "2026-06-27"
      ]
    },
    "1226157489405357205": {
      "nb": 1,
      "fr": 0,
      "newly": [
        "2026-06-17"
      ]
    },
    "1601820872618032450": {
      "nb": 5,
      "fr": 0,
      "newly": [
        "2026-07-04",
        "2026-07-05",
        "2026-07-06",
        "2026-09-28",
        "2026-09-29"
      ]
    },
    "3172003": {
      "nb": 1,
      "fr": 0,
      "newly": [
        "2026-06-19"
      ]
    }
  }
}